jeff65/__init__.py
jeff65/__main__.py
jeff65/ast.py
jeff65/immutable.py
jeff65/parsing.py
jeff65/pattern.py
jeff65/blum/__init__.py
jeff65/blum/fmt.py
jeff65/blum/image.py
jeff65/blum/linker.py
jeff65/blum/symbol.py
jeff65/blum/types.py
jeff65/gold/__init__.py
jeff65/gold/compiler.py
jeff65/gold/grammar.py
jeff65/gold/mem.py
jeff65/gold/units.py
jeff65/gold/passes/__init__.py
jeff65/gold/passes/asm.py
jeff65/gold/passes/binding.py
jeff65/gold/passes/lower.py
jeff65/gold/passes/resolve.py
jeff65/gold/passes/simplify.py
jeff65/gold/passes/typepasses.py
jeff65/mos6502/__init__.py
jeff65-0.0.1.dist-info/METADATA
jeff65-0.0.1.dist-info/RECORD
jeff65-0.0.1.dist-info/WHEEL
jeff65-0.0.1.dist-info/entry_points.txt
jeff65-0.0.1.dist-info/top_level.txt
