Metadata-Version: 2.1
Name: jeff65
Version: 0.0.1
Summary: A compiler targeting the Commodore 64
Home-page: https://github.com/jdpage/jeff65
Author: Jonathan David Page, Woodrow Barlow
Author-email: jeff65-maintainers@sleepingcyb.org
License: GNU General Public License v3 (GPLv3)
Platform: UNKNOWN
Classifier: Programming Language :: Python :: 3
Classifier: Programming Language :: Python :: 3.6
Requires-Dist: attrs (>=18.1.0)
